fog05rest/__init__.py
fog05rest/fimapi.py
fog05rest/fimerrors.py
fog05rest-0.0.4.dist-info/METADATA
fog05rest-0.0.4.dist-info/WHEEL
fog05rest-0.0.4.dist-info/top_level.txt
fog05rest-0.0.4.dist-info/RECORD
