Metadata-Version: 2.1
Name: fog05rest
Version: 0.0.4
Summary: Python API fog05 REST Client
Home-page: https://github.com/eclipse/fog05
Author: ADLINK
Author-email: UNKNOWN
License: Apache 2.O or EPL 2.0
Platform: UNKNOWN
Classifier: Development Status :: 2 - Pre-Alpha
Classifier: Intended Audience :: Developers
Classifier: Intended Audience :: Telecommunications Industry
Classifier: License :: OSI Approved :: Apache Software License
Classifier: License :: OSI Approved :: Eclipse Public License 2.0 (EPL-2.0)
Classifier: Programming Language :: Python :: 2
Classifier: Programming Language :: Python :: 3
Requires-Dist: requests
